wikionary/__init__.py
wikionary/wikionary.py
wikionary-1.2.1.dist-info/LICENSE
wikionary-1.2.1.dist-info/METADATA
wikionary-1.2.1.dist-info/WHEEL
wikionary-1.2.1.dist-info/top_level.txt
wikionary-1.2.1.dist-info/RECORD
