Metadata-Version: 2.1
Name: wikionary
Version: 1.2.1
Summary: Модуль для поиска Синонимов, Антонимов и т.д.
Home-page: https://github.com/DedInc/wikionary
Author: Maehdakvan
Author-email: visitanimation@google.com
Project-URL: Bug Tracker, https://github.com/DedInc/wikionary/issues
Classifier: Programming Language :: Python :: 3
Classifier: License :: OSI Approved :: MIT License
Classifier: Operating System :: OS Independent
Requires-Python: >=3.6
License-File: LICENSE
Requires-Dist: requests
Requires-Dist: lxml
Requires-Dist: pymorphy2
